dvm/__init__.py
dvm/dvm.py
dvm/dvm_eval.py
dvm/dvm_plot.py
dvm/elect.py
dvm/expec_votes.py
dvm/kings_ei.py
dvm/phc.py
dvm/prob_votes.py
dvm/tools.py
dvm-1.0.0.dist-info/LICENSE
dvm-1.0.0.dist-info/METADATA
dvm-1.0.0.dist-info/WHEEL
dvm-1.0.0.dist-info/top_level.txt
dvm-1.0.0.dist-info/RECORD
