Metadata-Version: 2.1
Name: dvm
Version: 1.0.0
Summary: The Discrete Voter Model for ecological inference.
Home-page: https://github.com/hangulu/dvm
Author: Hakeem Angulu
Author-email: hakeem.angulu@gmail.com
License: UNKNOWN
Keywords: voting,ecological inference,gerrymandering
Platform: UNKNOWN
Classifier: Programming Language :: Python :: 3
Classifier: License :: OSI Approved :: MIT License
Classifier: Operating System :: OS Independent
Requires-Python: >=3.7
Requires-Dist: numpy
Requires-Dist: pymc3
Requires-Dist: pandas
Requires-Dist: tqdm
Requires-Dist: tensorflow-probability
Requires-Dist: tensorflow
Requires-Dist: seaborn
